MANIFEST.in
README.md
logcat-color
setup.json
setup.py
logcat_color.egg-info/PKG-INFO
logcat_color.egg-info/SOURCES.txt
logcat_color.egg-info/dependency_links.txt
logcat_color.egg-info/requires.txt
logcat_color.egg-info/top_level.txt
logcatcolor/__init__.py
logcatcolor/column.py
logcatcolor/config.py
logcatcolor/format.py
logcatcolor/layout.py
logcatcolor/profile.py
logcatcolor/reader.py
test/test.py