Metadata-Version: 1.0
Name: logcat-color
Version: 0.6.0
Summary: A colorful alternative to "adb logcat"
Home-page: http://github.com/marshall/logcat-color
Author: Marshall Culpepper
Author-email: marshall.law@gmail.com
License: UNKNOWN
Platform: UNKNOWN
